david8_duckdb/__init__.py
david8_duckdb/joins.py
david8_duckdb/core/__init__.py
david8_duckdb/core/copy_to_query.py
david8_duckdb/core/dml.py
david8_duckdb/core/dql.py
david8_duckdb/core/export_db_query.py
david8_duckdb/core/joins.py
david8_duckdb/core/query_builder.py
david8_duckdb/core/query_options_processor.py
david8_duckdb/core/select_query.py
david8_duckdb/protocols/__init__.py
david8_duckdb/protocols/query_builder.py
david8_duckdb/protocols/sql.py
david8_duckdb-0.3.0b1.dist-info/METADATA
david8_duckdb-0.3.0b1.dist-info/WHEEL
david8_duckdb-0.3.0b1.dist-info/top_level.txt
david8_duckdb-0.3.0b1.dist-info/RECORD
